<?xml version='1.0'?>
<!--
  ~ Copyright 2000-2013 JetBrains s.r.o.
  ~ Copyright 2014-2014 AS3Boyan
  ~ Copyright 2014-2014 Elias Ku
  ~ Copyright 2019 Eric Bishton
  ~
  ~ Licensed under the Apache License, Version 2.0 (the "License");
  ~ you may not use this file except in compliance with the License.
  ~ You may obtain a copy of the License at
  ~
  ~ http://www.apache.org/licenses/LICENSE-2.0
  ~
  ~ Unless required by applicable law or agreed to in writing, software
  ~ distributed under the License is distributed on an "AS IS" BASIS,
  ~ WITHOUT WARRANTIES OR CONDITIONS OF ANY KIND, either express or implied.
  ~ See the License for the specific language governing permissions and
  ~ limitations under the License.
  -->
<list>
  <option name="HAXE_CONDITIONALLY_NOT_COMPILED">
    <value>
      <option name="FOREGROUND" value="38492E"/>
    </value>
  </option>
  <option name="HAXE_DEFINED_VAR">
    <value>
      <option name="FOREGROUND" value="38492E"/>
      <option name="FONT_TYPE" value="1"/>
    </value>
  </option>
  <option name="HAXE_UNDEFINED_VAR">
    <value>
      <option name="FOREGROUND" value="38492E"/>
    </value>
  </option>
  <option name="HAXE_UNPARSEABLE_DATA">
    <value>
      <option name="FOREGROUND" value="38492E"/>
      <option name="BACKGROUND" value="DADADA"/>
    </value>
  </option>
</list>
